sodespy/__init__.py
sodespy/noise.py
sodespy/sde_system.py
sodespy/timing.py
sodespy/schemes/SRA1.py
sodespy/schemes/SRI1W1.py
sodespy/schemes/__init__.py
sodespy/schemes/euler.py
sodespy/schemes/scheme_base.py
sodespy-0.0.1.dist-info/LICENSE
sodespy-0.0.1.dist-info/METADATA
sodespy-0.0.1.dist-info/WHEEL
sodespy-0.0.1.dist-info/top_level.txt
sodespy-0.0.1.dist-info/RECORD
