Metadata-Version: 2.1
Name: sodespy
Version: 0.0.1
Summary: SodesPy (Stochastic Ordinary Differential Equations Suite in Python) is a high-performance library for numerically solving stochastic differential equations (SDEs).
Home-page: https://github.com/mpkuperman/sodespy
Author: mpkuperman
Author-email: mpkuperman@gmail.com
License: UNKNOWN
Project-URL: Bug Tracker, https://github.com/mpkuperman/sodespy/issues
Platform: UNKNOWN
Requires-Python: >=3.6
License-File: LICENSE
